q/Ql2.py
q/Stopwatch_en.py
q/Stopwatch_ru.py
q/Timer.py
q/__init__.py
Quelert2-2.0.1.dist-info/METADATA
Quelert2-2.0.1.dist-info/WHEEL
Quelert2-2.0.1.dist-info/top_level.txt
Quelert2-2.0.1.dist-info/RECORD
