Metadata-Version: 2.1
Name: Quelert2
Version: 2.0.1
Summary: Ql2
Author: Georgy2008
Author-email: zadvornow2908@gmail.com
Classifier: Programming Language :: Python :: 3
Classifier: License :: OSI Approved :: MIT License
Classifier: Operating System :: OS Independent
Requires-Python: >=3.6
